pycord_ext_i18n/__init__.py
pycord_ext_i18n/enums.py
pycord_ext_i18n/errors.py
pycord_ext_i18n/i18n.py
pycord_ext_i18n/utils.py
pycord_ext_i18n-1.0.5.dist-info/METADATA
pycord_ext_i18n-1.0.5.dist-info/WHEEL
pycord_ext_i18n-1.0.5.dist-info/top_level.txt
pycord_ext_i18n-1.0.5.dist-info/RECORD
